Metadata-Version: 2.1
Name: bmstu-schedule-diff
Version: 1.2.0
Summary: Display BMSTU schedule diff
Home-page: https://github.com/trubitsyn/bmstu-schedule-diff
Author: Nikola Trubitsyn
Author-email: nikola.trubitsyn@gmail.com
License: UNKNOWN
Platform: UNKNOWN
Classifier: License :: OSI Approved :: GNU Affero General Public License v3 or later (AGPLv3+)
Classifier: Programming Language :: Python :: 3.6
Requires-Python: >=3.6
